{
  "data_asset_type": null,
  "expectation_suite_name": "suite_products",
  "expectations": [
    {
      "expectation_type": "expect_table_columns_to_match_set",
      "kwargs": {
        "column_set": [
          "Product_ID",
          "Product_Cost",
          "Product_Category",
          "Product_Name",
          "Product_Price"
        ]
      },
      "meta": {
        "profiler_details": {
          "success_ratio": 1.0
        }
      }
    },
    {
      "expectation_type": "expect_column_values_to_not_be_null",
      "kwargs": {
        "column": "Product_Cost"
      },
      "meta": {
        "profiler_details": {
          "metric_configuration": {
            "domain_kwargs": {
              "column": "Product_Cost"
            },
            "metric_name": "column_values.nonnull.unexpected_count",
            "metric_value_kwargs": null
          },
          "num_batches": 1
        }
      }
    },
    {
      "expectation_type": "expect_column_min_to_be_between",
      "kwargs": {
        "column": "Product_Cost",
        "min_value": 1,
        "strict_max": false,
        "strict_min": false
      },
      "meta": {
        "profiler_details": {
          "metric_configuration": {
            "domain_kwargs": {
              "column": "Product_Cost"
            },
            "metric_name": "column.min",
            "metric_value_kwargs": null
          },
          "num_batches": 1
        }
      }
    },
    {
      "expectation_type": "expect_column_values_to_match_regex",
      "kwargs": {
        "column": "Product_Cost",
        "mostly": 1.0,
        "regex": "^(?!\\$)\\d+\\.?\\d+$"
      },
      "meta": {}
    },
    {
      "expectation_type": "expect_column_values_to_not_be_null",
      "kwargs": {
        "column": "Product_Price"
      },
      "meta": {
        "profiler_details": {
          "metric_configuration": {
            "domain_kwargs": {
              "column": "Product_Price"
            },
            "metric_name": "column_values.nonnull.unexpected_count",
            "metric_value_kwargs": null
          },
          "num_batches": 1
        }
      }
    },
    {
      "expectation_type": "expect_column_min_to_be_between",
      "kwargs": {
        "column": "Product_Price",
        "min_value": 1,
        "strict_max": false,
        "strict_min": false
      },
      "meta": {
        "profiler_details": {
          "metric_configuration": {
            "domain_kwargs": {
              "column": "Product_Price"
            },
            "metric_name": "column.min",
            "metric_value_kwargs": null
          },
          "num_batches": 1
        }
      }
    },
    {
      "expectation_type": "expect_column_values_to_match_regex",
      "kwargs": {
        "column": "Product_Price",
        "mostly": 1.0,
        "regex": "^(?!\\$)\\d+\\.?\\d+$"
      },
      "meta": {}
    }
  ],
  "ge_cloud_id": null,
  "meta": {
    "citations": [
      {
        "citation_date": "2023-02-17T02:48:26.939109Z",
        "comment": "Created by effective Rule-Based Profiler of OnboardingDataAssistant with the configuration included.\n"
      }
    ],
    "great_expectations_version": "0.15.48"
  }
}